django_admin_filters/__init__.py
django_admin_filters/base.py
django_admin_filters/daterange.py
django_admin_filters/multi_choice.py
django_admin_filters/static/css/datetimepicker.css
django_admin_filters/static/js/datetimepicker.js
django_admin_filters/templates/base_admin_list_filter.html
django_admin_filters/templates/daterange.html
django_admin_filters/templates/daterange_picker.html
django_admin_filters/templates/multi_choice.html
django_admin_list_filters-1.3.1.dist-info/LICENSE
django_admin_list_filters-1.3.1.dist-info/METADATA
django_admin_list_filters-1.3.1.dist-info/WHEEL
django_admin_list_filters-1.3.1.dist-info/top_level.txt
django_admin_list_filters-1.3.1.dist-info/RECORD
