Metadata-Version: 2.1
Name: django-admin-list-filters
Version: 1.3.1
Summary: Embedded filters for Django Admin site
Home-page: https://github.com/vb64/django.admin.filters
Author: Vitaly Bogomolov
Author-email: mail@vitaly-bogomolov.ru
Project-URL: Bug Tracker, https://github.com/vb64/django.admin.filters/issues
Classifier: Programming Language :: Python :: 3
Classifier: License :: OSI Approved :: MIT License
Classifier: Operating System :: OS Independent
Requires-Python: >=3.7
License-File: LICENSE
